spherical_histogram/__init__.py
spherical_histogram/geometry.py
spherical_histogram/mesh.py
spherical_histogram/tree.py
spherical_histogram/version.py
spherical_histogram-0.1.6.dist-info/licenses/LICENSE
spherical_histogram-0.1.6.dist-info/METADATA
spherical_histogram-0.1.6.dist-info/WHEEL
spherical_histogram-0.1.6.dist-info/top_level.txt
spherical_histogram-0.1.6.dist-info/RECORD
