Metadata-Version: 2.4
Name: spherical_histogram
Version: 0.1.6
Summary: This is spherical_histogram.
Home-page: https://github.com/cherenkov-plenoscope/spherical_histogram
Author: Sebastian Achim Mueller
Author-email: sebastian-achim.mueller@mpi-hd.mpg.de
Classifier: Programming Language :: Python :: 3
Classifier: License :: OSI Approved :: MIT License
Classifier: Operating System :: OS Independent
Classifier: Natural Language :: English
License-File: LICENSE
Requires-Dist: spherical_coordinates>=0.1.6
Requires-Dist: solid_angle_utils>=0.1.2
Requires-Dist: binning_utils_sebastian-achim-mueller>=0.0.19
Requires-Dist: triangle_mesh_io>=0.0.4
Requires-Dist: merlict>=0.2.0.2.2.6
Requires-Dist: svg_cartesian_plot>=0.0.11
Dynamic: author
Dynamic: author-email
Dynamic: classifier
Dynamic: description
Dynamic: description-content-type
Dynamic: home-page
Dynamic: license-file
Dynamic: requires-dist
Dynamic: summary
